odoo/addons/res_company_gitlab_link/README.rst
odoo/addons/res_company_gitlab_link/__init__.py
odoo/addons/res_company_gitlab_link/__manifest__.py
odoo/addons/res_company_gitlab_link/i18n/fr.po
odoo/addons/res_company_gitlab_link/i18n/it.po
odoo/addons/res_company_gitlab_link/i18n/res_company_gitlab_link.pot
odoo/addons/res_company_gitlab_link/models/__init__.py
odoo/addons/res_company_gitlab_link/models/res_company.py
odoo/addons/res_company_gitlab_link/readme/CONTRIBUTORS.rst
odoo/addons/res_company_gitlab_link/readme/DESCRIPTION.rst
odoo/addons/res_company_gitlab_link/static/description/icon.png
odoo/addons/res_company_gitlab_link/static/description/index.html
odoo/addons/res_company_gitlab_link/views/view_res_company.xml
odoo_addon_res_company_gitlab_link-16.0.1.0.0.4.dist-info/METADATA
odoo_addon_res_company_gitlab_link-16.0.1.0.0.4.dist-info/WHEEL
odoo_addon_res_company_gitlab_link-16.0.1.0.0.4.dist-info/top_level.txt
odoo_addon_res_company_gitlab_link-16.0.1.0.0.4.dist-info/RECORD
